pyapk/__init__.py
pyapk/adboperations.py
pyapk/anim.py
pyapk/pyapk.py
pyapk-1.0.dist-info/DESCRIPTION.rst
pyapk-1.0.dist-info/METADATA
pyapk-1.0.dist-info/RECORD
pyapk-1.0.dist-info/WHEEL
pyapk-1.0.dist-info/entry_points.txt
pyapk-1.0.dist-info/metadata.json
pyapk-1.0.dist-info/top_level.txt
