Metadata-Version: 2.0
Name: pyapk
Version: 1.0
Summary: A simple program to install apks from a directory to android phone via adbSmall python program to install all apks on a directory(including apks in sub-directory of it) in your pc to android phones.
Home-page: https://github.com/psuzn/PyApk
Author: Sujan Poudel
Author-email: psuzzn@gmail.com
License: MIT
Download-URL: https://github.com/psuzn/PyApk
Keywords: adb,apk,install,android
Platform: UNKNOWN
Classifier: Environment :: Console
Classifier: Intended Audience :: Information Technology
Classifier: License :: OSI Approved :: MIT License
Classifier: Operating System :: OS Independent
Classifier: Programming Language :: Python
Classifier: Programming Language :: Python :: 3
